simplecrawl/__init__.py
simplecrawl/async_client.py
simplecrawl/models.py
simplecrawl/py.typed
simplecrawl/sync_client.py
firecrawl_simple_client-0.1.3.dist-info/LICENSE
firecrawl_simple_client-0.1.3.dist-info/METADATA
firecrawl_simple_client-0.1.3.dist-info/WHEEL
firecrawl_simple_client-0.1.3.dist-info/top_level.txt
firecrawl_simple_client-0.1.3.dist-info/RECORD
