Metadata-Version: 2.1
Name: firecrawl-simple-client
Version: 0.1.3
Summary: Python client for Firecrawl-Simple
Author-email: Darin <86675935+darinkishore@users.noreply.github.com>
License: MIT
Project-URL: Homepage, https://github.com/darinkishore/simplecrawl
Project-URL: Repository, https://github.com/darinkishore/simplecrawl
Project-URL: Documentation, https://github.com/darinkishore/simplecrawl#readme
Keywords: web-scraping,crawling,async,http
Classifier: Development Status :: 4 - Beta
Classifier: Intended Audience :: Developers
Classifier: License :: OSI Approved :: MIT License
Classifier: Programming Language :: Python :: 3
Classifier: Programming Language :: Python :: 3.10
Classifier: Programming Language :: Python :: 3.11
Classifier: Programming Language :: Python :: 3.12
Classifier: Topic :: Internet :: WWW/HTTP
Classifier: Topic :: Software Development :: Libraries :: Python Modules
Requires-Python: >=3.11
License-File: LICENSE
Requires-Dist: pydantic>=2.0.0
Requires-Dist: httpx>=0.24.0
Requires-Dist: requests>=2.32.3
Requires-Dist: python-dotenv>=1.0.1
